MANIFEST.in
README.rst
setup.py
smallBixTools/__init__.py
smallBixTools/describe.py
smallBixTools/haplotype_aligned_file.py
smallBixTools/mytests.py
smallBixTools/smallBixTools.py
smallBixTools/test_unittest.py
smallBixTools/trees.py
smallBixTools.egg-info/PKG-INFO
smallBixTools.egg-info/SOURCES.txt
smallBixTools.egg-info/dependency_links.txt
smallBixTools.egg-info/entry_points.txt
smallBixTools.egg-info/requires.txt
smallBixTools.egg-info/top_level.txt